{
  "rm-tag": {
    "prefix": "rmtag",
    "body": [
      "const strippedString = originalString.replace(/(<([^>]+)>)/gi, '');",
      ""
    ],
    "description": ""
  },
  "str-reverse": {
    "prefix": "srv",
    "body": [
      "function reverseString(string) {",
      "  return string.split(' ').reverse().join(' ');",
      "}",
      "",
      "revereseString();",
      ""
    ],
    "description": ""
  },
  "random": {
    "prefix": "rnd",
    "body": [
      "const rnd = Math.floor(Math.random() * items.length);",
      "items[rnd];",
      ""
    ],
    "description": ""
  }
}